{
  "command": "getValidPowerSwitchLocation",
  "is_cmd": true,
  "summary": "Gets valid power switch location.",
  "description": "Gets valid power switch location.",
  "usage": "getValidPowerSwitchLocation [-help] -cell <string> -loc <string> [-orient <string>] [-searchArea <string>]",
  "options": [
    {
      "name": "-help",
      "description": "Prints out the command usage",
      "required": false,
      "type": "flag"
    },
    {
      "name": "-cell",
      "description": "",
      "required": true,
      "type": "string"
    },
    {
      "name": "-loc",
      "description": "",
      "required": true,
      "type": "string"
    },
    {
      "name": "-orient",
      "description": "",
      "required": false,
      "type": "string"
    },
    {
      "name": "-searchArea",
      "description": "",
      "required": false,
      "type": "string"
    }
  ]
}