{
  "command": "setMultiCpuUsage",
  "is_cmd": true,
  "summary": "Sets multi cpu usage.",
  "description": "Sets multi cpu usage.",
  "usage": "setMultiCpuUsage [-help] [-acquireLicense <integer>] [-autoPageFaultMonitor {0 1 2 3}] [-cpuPerRemoteHost <integer>] [-gpuPerRemoteHost <integer>] [-keepLicense {true false}] [-licenseList <string>] [-localCpu <string>] [-localGpu <string>] [-localMem <string>] [-memPerRemoteHost <integer>] [-releaseLicense] [-remoteHost <integer>] [-reset] [-threadInfo {0 1 2}] [-verbose]",
  "options": [
    {
      "name": "-help",
      "description": "Prints out the command usage",
      "required": false,
      "type": "flag"
    },
    {
      "name": "-acquireLicense",
      "description": "Get the specified number of multi cpu licenses",
      "required": false,
      "type": "int"
    },
    {
      "name": "-autoPageFaultMonitor",
      "description": "Set the warning rank for performance issue caused by page fault (default=0)",
      "required": false,
      "type": "enum"
    },
    {
      "name": "-cpuPerRemoteHost",
      "description": "Number of CPUs available on every remote host (server)",
      "required": false,
      "type": "int"
    },
    {
      "name": "-gpuPerRemoteHost",
      "description": "Number of GPUs available on every remote host (server)",
      "required": false,
      "type": "int"
    },
    {
      "name": "-keepLicense",
      "description": "Set a flag to indicate whether the multicpu license should be kept or not",
      "required": false,
      "type": "enum"
    },
    {
      "name": "-licenseList",
      "description": "Specify the list/order of licenses the tool should use for multi cpu operations",
      "required": false,
      "type": "string"
    },
    {
      "name": "-localCpu",
      "description": "Number of available local CPUs (for distribution or threading)",
      "required": false,
      "type": "string"
    },
    {
      "name": "-localGpu",
      "description": "Number of available local GPUs (for distribution or threading)",
      "required": false,
      "type": "string"
    },
    {
      "name": "-localMem",
      "description": "Memory in MB available local GPUs (for distribution or threading)",
      "required": false,
      "type": "string"
    },
    {
      "name": "-memPerRemoteHost",
      "description": "Memory in MB available on every remote host (server)",
      "required": false,
      "type": "int"
    },
    {
      "name": "-releaseLicense",
      "description": "Release any multi cpu licenses",
      "required": false,
      "type": "flag"
    },
    {
      "name": "-remoteHost",
      "description": "Number of available remote hosts (servers)",
      "required": false,
      "type": "int"
    },
    {
      "name": "-reset",
      "description": "reset all distribute parameters",
      "required": false,
      "type": "flag"
    },
    {
      "name": "-threadInfo",
      "description": "Print informational thread messages",
      "required": false,
      "type": "enum"
    },
    {
      "name": "-verbose",
      "description": "Provide verbose messages when changing the settings",
      "required": false,
      "type": "flag"
    }
  ]
}