{
  "command": "changeBBoxMasterFromR0",
  "is_cmd": true,
  "summary": "Changes bbox master from r0.",
  "description": "Changes bbox master from r0.",
  "usage": "changeBBoxMasterFromR0 [-help] <cellName>",
  "options": [
    {
      "name": "<newOriginY>",
      "description": "<newOriginY>",
      "required": false,
      "type": "string"
    },
    {
      "name": "-help",
      "description": "Prints out the command usage",
      "required": false,
      "type": "flag"
    },
    {
      "name": "<cellName>",
      "description": "Specifies the name of the black box cell (string, required) {R90 R180 R270 MX MX90 MY MY90} # Specifies new orientation of cell",
      "required": true,
      "type": "enum"
    },
    {
      "name": "<newOriginX>",
      "description": "Specifies the new origin x-ordinate",
      "required": true,
      "type": "float"
    },
    {
      "name": "<newOriginY>",
      "description": "Specifies the new origin y-ordinate",
      "required": true,
      "type": "float"
    }
  ]
}