{
  "command": "saveWhatIfTimingAssertions",
  "is_cmd": true,
  "summary": "Saves what if timing assertions.",
  "description": "Saves what if timing assertions.",
  "usage": "saveWhatIfTimingAssertions [-help] {-outfile <outfile> | -tclList } { <blackBoxCellName>}",
  "options": [
    {
      "name": "-help",
      "description": "Prints out the command usage <blackBoxCellName> # name of the blackbox or blackblob cell",
      "required": false,
      "type": "string"
    },
    {
      "name": "-outfile",
      "description": "out file name",
      "required": false,
      "type": "string"
    },
    {
      "name": "-tclList",
      "description": "Generates the specifications as a Tcl list",
      "required": false,
      "type": "flag"
    }
  ]
}