{
  "command": "selectObjByProp",
  "is_cmd": true,
  "summary": "Selects obj by prop.",
  "description": "Selects obj by prop.",
  "usage": "selectObjByProp [-help]",
  "options": [
    {
      "name": "<expression>",
      "description": "<expression>",
      "required": false,
      "type": "string"
    },
    {
      "name": "-help",
      "description": "Prints out the command usage {Instance Pin Net Module InstanceGroup Bump Wire} The name of the object(s) on which the select operation is performed",
      "required": true,
      "type": "enum"
    },
    {
      "name": "<expression>",
      "description": "The selection criteria specified through the Find/Select Object form",
      "required": true,
      "type": "string"
    }
  ]
}