{
  "command": "registerTrigger",
  "is_cmd": true,
  "summary": "Registers trigger.",
  "description": "Registers trigger.",
  "usage": "registerTrigger [-help] [{-pre  | -post } <commandName> <procName>]",
  "options": [
    {
      "name": "-help",
      "description": "Prints out the command usage",
      "required": false,
      "type": "flag"
    },
    {
      "name": "<commandName>",
      "description": "Specifies command name",
      "required": true,
      "type": "string"
    },
    {
      "name": "<procName>",
      "description": "Specifies proc name",
      "required": true,
      "type": "string"
    },
    {
      "name": "-post",
      "description": "Specifies -post option",
      "required": true,
      "type": "flag"
    },
    {
      "name": "-pre",
      "description": "Specifies -pre option",
      "required": true,
      "type": "flag"
    }
  ]
}