{
  "command": "set_power_output_dir",
  "is_cmd": true,
  "summary": "Sets power output dir.",
  "description": "Sets power output dir.",
  "usage": "set_power_output_dir [-help] [<dir>] [-reset]",
  "options": [
    {
      "name": "-help",
      "description": "Prints out the command usage",
      "required": false,
      "type": "flag"
    },
    {
      "name": "<dir>",
      "description": "output directory",
      "required": false,
      "type": "string"
    },
    {
      "name": "-reset",
      "description": "reset all options",
      "required": false,
      "type": "flag"
    }
  ]
}