{
  "command": "dumpMultiBitFlopMappingFile",
  "is_cmd": true,
  "summary": "Dumps multi bit flop mapping file.",
  "description": "Dumps multi bit flop mapping file.",
  "usage": "dumpMultiBitFlopMappingFile [-help] [-mapOutputPins {false true all}] [-output <directory>] [-prefix <fileName_prefix>]",
  "options": [
    {
      "name": "-help",
      "description": "Prints out the command usage",
      "required": false,
      "type": "flag"
    },
    {
      "name": "-mapOutputPins",
      "description": "Dump mapped output terms in MBFF pin mapping file. Default is false",
      "required": false,
      "type": "enum"
    },
    {
      "name": "-output",
      "description": "Specifies the directory to dump MBFF mapping files. Default is current directory.",
      "required": false,
      "type": "string"
    },
    {
      "name": "-prefix",
      "description": "Specifies the prefix to the MBFF mapping files. Default is none.",
      "required": false,
      "type": "string"
    }
  ]
}