{
  "command": "reportFootPrint",
  "is_cmd": true,
  "summary": "Reports foot print.",
  "description": "Reports foot print.",
  "usage": "reportFootPrint [-help] [<footprint>] [-dontTouchNUse] [-outfile <string>]",
  "options": [
    {
      "name": "-help",
      "description": "Prints out the command usage <footprint> # to report a specific footprint",
      "required": false,
      "type": "string"
    },
    {
      "name": "-dontTouchNUse",
      "description": "print dont_touch and dont_true cells",
      "required": false,
      "type": "flag"
    },
    {
      "name": "-outfile",
      "description": "output file name",
      "required": false,
      "type": "string"
    }
  ]
}