{
  "command": "reportDeCap",
  "is_cmd": true,
  "summary": "Reports de cap.",
  "description": "Reports de cap.",
  "usage": "reportDeCap [-help] [ -area <llx> <lly> <urx> <ury> ]",
  "options": [
    {
      "name": "-help",
      "description": "Prints out the command usage",
      "required": false,
      "type": "flag"
    },
    {
      "name": "-area",
      "description": "Defines an area for which to report placed decoupling capacitance cells.",
      "required": false,
      "type": "point"
    }
  ]
}