{
  "command": "set_annotated_delay",
  "is_cmd": true,
  "summary": "Sets annotated delay.",
  "description": "Sets annotated delay.",
  "usage": "set_annotated_delay [-help] <delay_value> [-cond <expression>] [-delta_only] [-fall] [-increment] [-max] [-min] [-rise] {-net  | -cell } { [-from <from_pins>]  [-to <to_pins>]}",
  "options": [
    {
      "name": "-help",
      "description": "Prints out the command usage <delay_value> # Specifies the delay value to be applied",
      "required": true,
      "type": "float"
    },
    {
      "name": "-cell",
      "description": "Specifies the annotated delay is to be applied on cell",
      "required": false,
      "type": "flag"
    },
    {
      "name": "-cond",
      "description": "Specifies that annotated delay is applied on arcs which has this condition as true",
      "required": false,
      "type": "string"
    },
    {
      "name": "-delta_only",
      "description": "Specifies that annotated delay is applied as incremental delay",
      "required": false,
      "type": "flag"
    },
    {
      "name": "-fall",
      "description": "Specifies the annotated delay is applicable on fall transisiton",
      "required": false,
      "type": "flag"
    },
    {
      "name": "-from",
      "description": "Specifies that annotated delay is applied on arcs from this pin",
      "required": false,
      "type": "string"
    },
    {
      "name": "-increment",
      "description": "Increments the specified delay value on top of the existing base delay value",
      "required": false,
      "type": "flag"
    },
    {
      "name": "-max",
      "description": "Specifies that annotated delay is applicable on late paths",
      "required": false,
      "type": "flag"
    },
    {
      "name": "-min",
      "description": "Specifies that annotated delay is applicable on early paths",
      "required": false,
      "type": "flag"
    },
    {
      "name": "-net",
      "description": "Specifies the annotated delay is to be applied on net",
      "required": false,
      "type": "flag"
    },
    {
      "name": "-rise",
      "description": "Specifies the annotated delay is applicable on rise transisiton",
      "required": false,
      "type": "flag"
    },
    {
      "name": "-to",
      "description": "Specifies that annotated delay is applied on arcs to this pin",
      "required": false,
      "type": "string"
    }
  ]
}