{
  "command": "editTrim",
  "is_cmd": true,
  "summary": "修剪（移除）版图中的特殊连线或悬空线头。",
  "description": "该命令用于修剪版图中的特殊连线（special wires）和悬空线头（floating stubs）。用户可以通过多种选项指定修剪的范围，例如修剪所有对象、仅修剪选中的对象、修剪特定网络或特定层上的对象，也可以指定一个矩形区域进行修剪。此外，还可以根据连线的状态（如已布线、屏蔽等）或类型（如悬空线）进行筛选。",
  "usage": "editTrim [-help] [-keep_floating_stubs] [-status {COVER FIXED NOSHIELD ROUTED SHIELD}] [-type {float}] [-all  | -selected  | -nets <net>*] [-all  | -selected  | -layers <string>] [-all  | -selected  | -area {x1 y1 x2 y2}]",
  "options": [
    {
      "name": "-help",
      "description": "打印此命令的使用说明。",
      "required": false,
      "type": "flag"
    },
    {
      "name": "-keep_floating_stubs",
      "description": "指定在修剪时是否保留悬空线头。",
      "required": false,
      "type": "flag"
    },
    {
      "name": "-status",
      "description": "指定要修剪的连线的状态。可选值包括：COVER, FIXED, NOSHIELD, ROUTED, SHIELD。",
      "required": false,
      "type": "enum"
    },
    {
      "name": "-type",
      "description": "指定修剪类型为移除悬空线，即移除那些未与其他连线或引脚建立电气连接的连线。",
      "required": false,
      "type": "enum"
    },
    {
      "name": "-all",
      "description": "指定修剪所有符合条件的特殊连线和悬空线头。",
      "required": false,
      "type": "flag"
    },
    {
      "name": "-selected",
      "description": "指定仅修剪当前选中的连线。",
      "required": false,
      "type": "flag"
    },
    {
      "name": "-nets",
      "description": "指定要修剪的连线所属的网络名称列表。",
      "required": false,
      "type": "net+"
    },
    {
      "name": "-layers",
      "description": "指定要从哪些金属层上修剪连线。",
      "required": false,
      "type": "string"
    },
    {
      "name": "-area",
      "description": "指定一个矩形区域（通过左下角坐标x1 y1和右上角坐标x2 y2定义），仅修剪该区域内的连线。",
      "required": false,
      "type": "box"
    }
  ]
}