{
  "command": "reportInstPad",
  "is_cmd": true,
  "summary": "报告实例填充信息",
  "description": "此命令用于报告指定实例或所有实例的填充（padding）信息。填充通常指在物理设计阶段，为满足设计规则或性能要求而在标准单元或宏块周围添加的额外空间。",
  "usage": "reportInstPad [-help] {-all  | <instName>}",
  "options": [
    {
      "name": "-help",
      "description": "打印命令用法",
      "required": false,
      "type": "flag"
    },
    {
      "name": "<instName>",
      "description": "报告给定实例的填充信息（字符串类型，必需参数）",
      "required": true,
      "type": "string"
    },
    {
      "name": "-all",
      "description": "报告所有具有填充的实例（布尔类型，必需参数）",
      "required": true,
      "type": "flag"
    }
  ]
}