{
  "command": "gui_schematic_load_view",
  "is_cmd": true,
  "summary": "加载原理图视图",
  "description": "该命令用于加载指定的原理图视图文件，并可在图形界面中打开。可以通过 -file 参数指定要加载的文件路径，并通过可选的 -name 参数为打开的视图窗口指定一个唯一的名称。",
  "usage": "gui_schematic_load_view [-help] -file <string> [-name <string>]",
  "options": [
    {
      "name": "-help",
      "description": "打印此命令的使用说明",
      "required": false,
      "type": "flag"
    },
    {
      "name": "-file",
      "description": "指定要加载的原理图视图文件路径",
      "required": true,
      "type": "string"
    },
    {
      "name": "-name",
      "description": "为打开的视图窗口指定一个唯一的名称",
      "required": false,
      "type": "string"
    }
  ]
}