{
  "command": "get_constant_for_timing",
  "is_cmd": true,
  "summary": "获取指定引脚在时序分析中使用的恒定值（常量）",
  "description": "此命令用于查询指定引脚（pin）在时序分析（timing analysis）中被设置为何种恒定逻辑值（例如逻辑0或逻辑1）。这对于分析具有固定驱动或接收状态的引脚（特别是双向引脚）的时序影响非常有用。命令可以指定是查询双向引脚的输入部分还是输出部分的常量值。",
  "usage": "get_constant_for_timing [-help] <pin_name> [-bidi_input  | -bidi_output ]",
  "options": [
    {
      "name": "-help",
      "description": "打印此命令的使用说明",
      "required": false,
      "type": "flag"
    },
    {
      "name": "<pin_name>",
      "description": "需要查询其状态的单个引脚的名称",
      "required": true,
      "type": "string"
    },
    {
      "name": "-bidi_input",
      "description": "返回设置在双向引脚输入部分的常量值",
      "required": false,
      "type": "flag"
    },
    {
      "name": "-bidi_output",
      "description": "返回设置在双向引脚输出部分的常量值",
      "required": false,
      "type": "flag"
    }
  ]
}