{
  "command": "create_thermal_model",
  "is_cmd": true,
  "summary": "创建热模型",
  "description": "该命令用于创建热模型，需要额外的 vtsaa (Voltus_Power_Integrity_AA) 许可证。它允许用户指定泄漏温度缩放表、金属密度文件、功率数据库以及各种VTM（热模型）相关的参数，如格式、版本、输出目录和瓦片大小等，以生成用于热分析的热模型文件。",
  "usage": "create_thermal_model [-help] [-leakage_temperature_scale_table <string>] [-leakage_temperature_scale_table_file <string>] [-metal_density_file <string>] [-power_db <string>] [-vtm_SI_unit <string>] [-vtm_conductivity_inputs <string>] [-vtm_densitytable_tile <string>] [-vtm_file <string>] [-vtm_format <string>] [-vtm_format_version <string>] [-vtm_header_include_file <string>] [-vtm_leakage_temp <string>] [-vtm_output_dir <string>] [-vtm_powertable_tile <string>] [-vtm_tile <string>] [-vtm_tile_size <string>]",
  "options": [
    {
      "name": "-help",
      "description": "打印命令用法",
      "required": false,
      "type": "flag"
    },
    {
      "name": "-leakage_temperature_scale_table",
      "description": "泄漏温度缩放表（字符串，可选）",
      "required": false,
      "type": "string"
    },
    {
      "name": "-leakage_temperature_scale_table_file",
      "description": "泄漏温度缩放表文件（字符串，可选）",
      "required": false,
      "type": "string"
    },
    {
      "name": "-metal_density_file",
      "description": "金属密度文本文件路径（字符串，可选）",
      "required": false,
      "type": "string"
    },
    {
      "name": "-power_db",
      "description": "功率数据库路径（字符串，可选）",
      "required": false,
      "type": "string"
    },
    {
      "name": "-vtm_SI_unit",
      "description": "使用SI单位（字符串，可选）",
      "required": false,
      "type": "string"
    },
    {
      "name": "-vtm_conductivity_inputs",
      "description": "VTM电导率文件名（字符串，可选）",
      "required": false,
      "type": "string"
    },
    {
      "name": "-vtm_densitytable_tile",
      "description": "金属表瓦片大小（字符串，可选）",
      "required": false,
      "type": "string"
    },
    {
      "name": "-vtm_file",
      "description": "输出文件名（字符串，可选）",
      "required": false,
      "type": "string"
    },
    {
      "name": "-vtm_format",
      "description": "VTM数据格式（字符串，可选）",
      "required": false,
      "type": "string"
    },
    {
      "name": "-vtm_format_version",
      "description": "新/默认格式（字符串，可选）",
      "required": false,
      "type": "string"
    },
    {
      "name": "-vtm_header_include_file",
      "description": "头文件包含（字符串，可选）",
      "required": false,
      "type": "string"
    },
    {
      "name": "-vtm_leakage_temp",
      "description": "泄漏温度（字符串，可选）",
      "required": false,
      "type": "string"
    },
    {
      "name": "-vtm_output_dir",
      "description": "输出目录名（字符串，可选）",
      "required": false,
      "type": "string"
    },
    {
      "name": "-vtm_powertable_tile",
      "description": "功率表瓦片大小（字符串，可选）",
      "required": false,
      "type": "string"
    },
    {
      "name": "-vtm_tile",
      "description": "瓦片大小 {intX intY}（字符串，可选）",
      "required": false,
      "type": "string"
    },
    {
      "name": "-vtm_tile_size",
      "description": "单个瓦片大小 {Xsize Ysize}（字符串，可选）",
      "required": false,
      "type": "string"
    }
  ]
}