{
  "command": "setMultiColorsHier",
  "is_cmd": true,
  "summary": "设置或重置层次化实例的颜色ID",
  "description": "此命令用于将指定的层次化实例或所有层次化实例重置到给定的颜色ID。颜色ID是一个可选参数，用于定义颜色标识；层次化实例名称也是一个可选参数，用于指定特定的实例。",
  "usage": "setMultiColorsHier [-help] [<colorID> [<hInstName>]]",
  "options": [
    {
      "name": "-help",
      "description": "打印命令的使用说明",
      "required": false,
      "type": "flag"
    },
    {
      "name": "<colorID>",
      "description": "颜色ID，用于重置所有层次化实例或指定层次化实例的颜色（整数，可选，范围0-29）",
      "required": false,
      "type": "int"
    },
    {
      "name": "<hInstName>",
      "description": "层次化实例的名称（字符串，可选）",
      "required": false,
      "type": "string"
    }
  ]
}