{
  "command": "read_sai",
  "is_cmd": true,
  "summary": "读取SAI文件",
  "description": "该命令用于读取SAI（Standard Abstract Information）文件。SAI文件包含设计的抽象信息，可用于恢复设计状态或导入特定规则。命令支持指定文件名、处理部分加载的设计、根据flexfiller进行简化以及仅导入规则等选项。",
  "usage": "read_sai [-help] [<name>] [-partial] [-reduce_by_flexfiller] [-rule_only]",
  "options": [
    {
      "name": "-help",
      "description": "打印此命令的使用说明",
      "required": false,
      "type": "flag"
    },
    {
      "name": "<name>",
      "description": "指定要读取的SAI文件名",
      "required": false,
      "type": "string"
    },
    {
      "name": "-partial",
      "description": "指示设计是通过restoreDesign命令加载的，属于部分加载状态",
      "required": false,
      "type": "flag"
    },
    {
      "name": "-reduce_by_flexfiller",
      "description": "指定是否根据flexfiller的使用情况进行简化处理",
      "required": false,
      "type": "flag"
    },
    {
      "name": "-rule_only",
      "description": "仅导入SAI文件中的规则部分",
      "required": false,
      "type": "flag"
    }
  ]
}