{
  "command": "setResizeLine",
  "is_cmd": true,
  "summary": "设置用于基于位移的版图调整的重调线",
  "description": "此命令用于为 `resizeFloorplan` 命令的基于位移的版图调整选项设置重调线。重调线可以是非连续的，但必须是正交的。如果指定了重调线，版图将在重调线指定的区域之间进行调整（用于基于位移的版图调整）。要在水平方向收缩或扩展版图，需指定垂直重调线；要在垂直方向收缩或扩展版图，需指定水平重调线。每条重调线可以包含多个线段（例如，水平、垂直、再水平），但只能应用于一个方向。若要在两个方向调整版图，需为每个方向指定重调线。可以创建多条重调线。重调线在 `resizeFloorplan` 命令运行后会被移除。可以在导入设计后使用此命令。",
  "usage": "setResizeLine [-help] -clearAll [-direction {H|V}] [<points>] [-width <float>]",
  "options": [
    {
      "name": "-help",
      "description": "输出包含每个 setResizeLine 参数类型和默认值的简要描述。如需命令及其所有参数的详细描述，请使用 man 命令。",
      "required": false,
      "type": "flag"
    },
    {
      "name": "-clearAll",
      "description": "清除所有重调线。",
      "required": false,
      "type": "flag"
    },
    {
      "name": "-direction",
      "description": "指定重调线是水平（H）还是垂直（V）。",
      "required": false,
      "type": "string"
    },
    {
      "name": "<points>",
      "description": "指定重调线的点列表。",
      "required": false,
      "type": "pt list"
    },
    {
      "name": "-width",
      "description": "以微米为单位指定重调线的宽度。正值扩展版图，负值收缩版图。",
      "required": false,
      "type": "float"
    }
  ]
}