{
  "command": "createPinGuide",
  "is_cmd": true,
  "summary": "创建引脚引导对象",
  "description": "创建一个引脚引导对象。引脚引导将限制与引导相关联的引脚在指定的区域内。此命令也可在顶层模块上运行。您可以将同一个引脚组或网络组分配给多个引脚引导。引脚引导会为总线、网络、网络组、引脚和引脚组生成。对于未物理连接到分区的总线和网络，将不会创建引脚引导。您可以在分区布局规划期间使用此命令。",
  "usage": "createPinGuide [-help] {[ -area {<x1 y1 x2 y2>} | [-edge <integer> [[-offset_start <float>] [-offset_end <float>]]]] [ -layer {<layeridList>} [-layerPriority ]]} [-pin <string> | -pinGroup <string> | -net <string> | -netGroup <string> | -name <string> ] [-edge <integer> | -net <string> | -netGroup <string>] [-cell <string> | -net <string> | -netGroup <string>]",
  "options": [
    {
      "name": "-area",
      "description": "指定引脚引导区域的坐标。",
      "required": false,
      "type": "rect"
    },
    {
      "name": "-cell",
      "description": "指定单元的名称。如果在顶层模块上使用此命令，则不需要此参数。",
      "required": false,
      "type": "string"
    },
    {
      "name": "-edge",
      "description": "指定从分区左下角顺时针开始计数的边编号整数值。边0是具有最小y值的边。",
      "required": false,
      "type": "int"
    },
    {
      "name": "-help",
      "description": "输出包含每个createPinGuide参数类型和默认信息的简要描述。",
      "required": false,
      "type": "flag"
    },
    {
      "name": "-layer",
      "description": "指定引脚引导的金属层。",
      "required": false,
      "type": "string"
    },
    {
      "name": "-layerPriority",
      "description": "根据用户指定的-layer顺序分配引脚。",
      "required": false,
      "type": "flag"
    },
    {
      "name": "-name",
      "description": "指定分区引脚引导对象的名称。如果指定此参数，命令将自动检测对象是引脚、引脚组、网络、网络组还是总线。",
      "required": false,
      "type": "string"
    },
    {
      "name": "-net",
      "description": "对于网络，指定网络名称。对于总线，指定总线名称或总线基数。",
      "required": false,
      "type": "string"
    },
    {
      "name": "-netGroup",
      "description": "指定网络组的名称。",
      "required": false,
      "type": "string"
    },
    {
      "name": "-offset_end",
      "description": "指定距离边结束角的距离，单位为微米。",
      "required": false,
      "type": "float"
    },
    {
      "name": "-offset_start",
      "description": "指定距离边起始角的距离，单位为微米。",
      "required": false,
      "type": "float"
    },
    {
      "name": "-pin",
      "description": "指定引脚的名称。",
      "required": false,
      "type": "string"
    },
    {
      "name": "-pinGroup",
      "description": "指定引脚组的名称。",
      "required": false,
      "type": "string"
    }
  ]
}