{
  "command": "reset_disable_timing",
  "is_cmd": true,
  "summary": "恢复被 set_disable_timing 命令禁用的时序弧",
  "description": "该命令用于恢复之前通过 set_disable_timing 命令禁用的时序弧。可以指定对象列表（如实例、实例引脚、库单元、库单元引脚等），并可选择性地使用 -from 和 -to 参数来指定要恢复的特定时序弧路径。",
  "usage": "reset_disable_timing [-help] [-from <pin_name> -to <pin_name>] <object_list>",
  "options": [
    {
      "name": "-help",
      "description": "打印命令用法信息。",
      "required": false,
      "type": "flag"
    },
    {
      "name": "-from",
      "description": "与 -to 参数一起使用，指定要恢复的时序弧的起始引脚名。当对象列表包含实例或库单元对象时，可以指定此参数。",
      "required": false,
      "type": "string"
    },
    {
      "name": "-to",
      "description": "与 -from 参数一起使用，指定要恢复的时序弧的终止引脚名。当对象列表包含实例或库单元对象时，可以指定此参数。",
      "required": false,
      "type": "string"
    },
    {
      "name": "<object_list>",
      "description": "指定要操作的对象列表，可以是实例、实例引脚、库弧、库单元或库单元引脚对象。",
      "required": true,
      "type": "inst+"
    }
  ]
}