{
  "command": "flipOrRotateObject",
  "is_cmd": true,
  "summary": "翻转或旋转选中的对象",
  "description": "该命令用于翻转或旋转选中的对象。作为替代方案，也可以在Innovus图形用户界面中使用“翻转/旋转选中对象”表单来翻转或旋转一个实例。此命令通常在导入设计后使用。",
  "usage": "flipOrRotateObject [-help] [-keepRelative] {-flip {MX | MY} | -rotate {R90 | R180 | R270}} [-group] [-name <object>]",
  "options": [
    {
      "name": "-help",
      "description": "输出包含每个flipOrRotateObject参数类型和默认信息的简要描述。如需命令及其所有参数的详细描述，请使用man命令。",
      "required": false,
      "type": "flag"
    },
    {
      "name": "-keepRelative",
      "description": "调用create_relative_floorplan命令。启用此选项后，当锚点对象被旋转时，相关对象会自动旋转和更新。",
      "required": false,
      "type": "flag"
    },
    {
      "name": "-flip",
      "description": "沿X轴或Y轴翻转选中的对象。",
      "required": true,
      "type": "string"
    },
    {
      "name": "-rotate",
      "description": "将选中的对象旋转90度、180度或270度。",
      "required": true,
      "type": "string"
    },
    {
      "name": "-group",
      "description": "翻转或旋转包围所有选中对象的边界框。",
      "required": false,
      "type": "flag"
    },
    {
      "name": "-name",
      "description": "指定要翻转或旋转的对象的名称。注意：对象可以是模块、组、布局阻挡、布线阻挡、硬宏、特殊布线、特殊连线以及特殊通孔（包括45度）。",
      "required": false,
      "type": "string"
    }
  ]
}