{
  "command": "adjustFPlanChannel",
  "is_cmd": true,
  "summary": "自动调整对象间的通道宽度以防止潜在的布线拥塞",
  "description": "该命令用于自动调整布局规划中对象（如宏模块、围栏、核心区域）之间的通道宽度，以防止潜在的布线拥塞。通常在导入设计、加载完成的布局规划、并运行 place_design 和 earlyGlobalRoute 命令后使用。",
  "usage": "adjustFPlanChannel [-help] [-channelUtil <utilizationValue>] [-constraints <constraint_file>] [-moveOnly] [-report <output_file>] [-reportOnly [-report_low_utilized_channels <value>] [-type {all fenceToFence fenceToCore fenceToMacro macroToMacro macroToCore}]]",
  "options": [
    {
      "name": "-help",
      "description": "输出包含每个参数类型和默认信息的简要描述。",
      "required": false,
      "type": "flag"
    },
    {
      "name": "-channelUtil",
      "description": "指定通道中布线轨道的最大利用率。",
      "required": false,
      "type": "float"
    },
    {
      "name": "-constraints",
      "description": "指定包含布局规划对象约束的文件。",
      "required": false,
      "type": "string"
    },
    {
      "name": "-moveOnly",
      "description": "指定仅允许进行移动调整。",
      "required": false,
      "type": "flag"
    },
    {
      "name": "-report",
      "description": "生成包含通道拥塞情况、目标通道调整和最终实际布局规划调整的报告。",
      "required": false,
      "type": "string"
    },
    {
      "name": "-reportOnly",
      "description": "仅生成通道拥塞报告，不调整布局规划。",
      "required": false,
      "type": "flag"
    },
    {
      "name": "-report_low_utilized_channels",
      "description": "报告轨道利用率低于用户指定阈值的通道拥塞情况。",
      "required": false,
      "type": "float"
    },
    {
      "name": "-type",
      "description": "报告指定类型的通道拥塞情况。可以同时指定多种类型。",
      "required": false,
      "type": "enum_list"
    }
  ]
}