{
  "command": "setPinDensityMapMode",
  "is_cmd": true,
  "summary": "设置 reportPinDensityMap 命令的全局参数",
  "description": "为 reportPinDensityMap 命令设置全局参数。通过 setPinDensityMapMode 指定的参数将在运行 reportPinDensityMap 时被使用。reportPinDensityMap 命令本身指定的参数将覆盖 setPinDensityMapMode 命令设置的参数。",
  "usage": "setPinDensityMapMode [-help] [-reset] [-displayStep <step_value>] [-gridInMicron <micron>] [-gridInRow <numberRow>] [-threshold <density>]",
  "options": [
    {
      "name": "-help",
      "description": "输出包含每个参数类型和默认值的简要描述。",
      "required": false,
      "type": "flag"
    },
    {
      "name": "-reset",
      "description": "将所有或指定的选项重置为默认值。任何被重置且与默认值不同的值将被报告。",
      "required": false,
      "type": "flag"
    },
    {
      "name": "-displayStep",
      "description": "指定用于显示引脚密度图计算的范围步长。默认值：0.05",
      "required": false,
      "type": "float"
    },
    {
      "name": "-gridInMicron",
      "description": "指定用于引脚密度计算的方形网格边长值（单位：微米）。默认值：50，最小值：0.000000，最大值：1000.000000",
      "required": false,
      "type": "float"
    },
    {
      "name": "-gridInRow",
      "description": "指定用于引脚密度计算的方形网格边长值（单位：行高）。默认值：10，最小值：1，最大值：100",
      "required": false,
      "type": "int"
    },
    {
      "name": "-threshold",
      "description": "指定必须报告的密度阈值。默认值：0.5",
      "required": false,
      "type": "float"
    }
  ]
}