{
  "command": "set_input_delay",
  "is_cmd": true,
  "summary": "定义输入端口或内部输入引脚相对于时钟边沿的到达时间",
  "description": "此命令用于定义输入端口或内部输入引脚相对于时钟边沿的到达时间。该输入路径延迟用于建模从外部寄存器到模块输入端口之间的延迟。如果未在输入端口上指定输入延迟，则假定为零。",
  "usage": "set_input_delay [-clock <clock_name>] [-clock_fall] [-rise] [-fall] [-max] [-min] [-add_delay] [-network_latency_included] [-source_latency_included] [-reference_pin <pin_name>] [-level_sensitive] <delay_value> <port_or_pin_list>",
  "options": [
    {
      "name": "-clock",
      "description": "指定延迟相对于给定时钟的上升沿。如果未指定此参数，则延迟相对于时间零。",
      "required": false,
      "type": "string"
    },
    {
      "name": "-clock_fall",
      "description": "指定延迟相对于时钟的下降沿。必须与 -clock 参数一起使用。",
      "required": false,
      "type": "flag"
    },
    {
      "name": "-rise",
      "description": "指定输入延迟适用于指定端口或引脚信号的上升沿。",
      "required": false,
      "type": "flag"
    },
    {
      "name": "-fall",
      "description": "指定输入延迟适用于指定端口或引脚信号的下降沿。",
      "required": false,
      "type": "flag"
    },
    {
      "name": "-max",
      "description": "指定延迟用于建立时间分析。",
      "required": false,
      "type": "flag"
    },
    {
      "name": "-min",
      "description": "指定延迟用于保持时间分析。",
      "required": false,
      "type": "flag"
    },
    {
      "name": "-add_delay",
      "description": "将延迟信息添加到现有的输入延迟中。用于同一端口或引脚存在多个相对于不同时钟或时钟边沿的路径延迟时。",
      "required": false,
      "type": "flag"
    },
    {
      "name": "-network_latency_included",
      "description": "指定时钟网络延迟不应添加到输入延迟值中。如果未指定此选项，相关时钟的时钟网络延迟会被添加到输入延迟值中。",
      "required": false,
      "type": "flag"
    },
    {
      "name": "-source_latency_included",
      "description": "指定时钟源延迟不应添加到输入延迟值中。",
      "required": false,
      "type": "flag"
    },
    {
      "name": "-reference_pin",
      "description": "在传播模式下，将指定参考引脚（reference pin）的源延迟和网络延迟添加到输入延迟值中。参考引脚是指定时钟源扇出锥中的叶引脚。",
      "required": false,
      "type": "string"
    },
    {
      "name": "-level_sensitive",
      "description": "对由正电平敏感锁存器触发的输入延迟进行建模。必须与 -clock 参数一起使用。",
      "required": false,
      "type": "flag"
    }
  ]
}