{
  "command": "setSelectedDensityArea",
  "is_cmd": true,
  "summary": "为选定的密度屏区域指定属性",
  "description": "此命令用于指定选定密度屏区域的属性。导入设计并选择密度区域后，如果需要，可以使用此命令更改密度区域的位置、类型或密度。",
  "usage": "setSelectedDensityArea [-help] <x1 y1 x2 y2> <density> <name> {Partial Soft Hard} {Instance Pushdown Undefined}",
  "options": [
    {
      "name": "-help",
      "description": "输出包含每个setSelectedDensityArea参数类型和默认信息的简要描述。",
      "required": false,
      "type": "flag"
    },
    {
      "name": "<x1 y1 x2 y2>",
      "description": "指定密度屏区域的坐标。",
      "required": true,
      "type": "float"
    },
    {
      "name": "<density>",
      "description": "指定标准单元布局密度百分比。有效值以5为增量：0, 5, 10, ...100。例如，设置密度百分比为75%意味着定义的密度区域最多75%将用于布局。注意：如果输入任何无效数字，百分比将默认为最接近的有效值。",
      "required": true,
      "type": "float"
    },
    {
      "name": "<name>",
      "description": "指定密度屏区域的名称。",
      "required": true,
      "type": "string"
    },
    {
      "name": "{Partial Soft Hard}",
      "description": "指定密度屏区域的硬度。",
      "required": false,
      "type": "enum"
    },
    {
      "name": "{Instance Pushdown Undefined}",
      "description": "指定密度屏区域与设计的关系。* Instance：密度屏区域与当前设计关联。* Pushdown：密度屏区域从层次结构中推下。* Undefined：密度屏区域与设计的关系未定义。默认值：Undefined。",
      "required": false,
      "type": "enum"
    }
  ]
}