{
  "command": "deleteScanChainPartition",
  "is_cmd": true,
  "summary": "删除扫描链分区",
  "description": "删除扫描链分区。分区用于对扫描链进行分组，以便可以交换兼容扫描链中的元素。然后，扫描链将在每条链的基础上重新排序。使用 specifyScanChainPartition 命令来指定扫描链分区。",
  "usage": "deleteScanChainPartition [-help] {-all | -partition <partitionName1 partitionName2 ...>}",
  "options": [
    {
      "name": "-help",
      "description": "显示此命令的帮助信息",
      "required": false,
      "type": "flag"
    },
    {
      "name": "-all",
      "description": "从兼容组中删除所有分区",
      "required": false,
      "type": "flag"
    },
    {
      "name": "-partition",
      "description": "指定要删除的分区名称列表",
      "required": false,
      "type": "string"
    }
  ]
}