{
  "command": "register_gui_edit_callback",
  "is_cmd": true,
  "summary": "为指定的移动操作添加回调函数",
  "description": "此命令用于为图形用户界面（GUI）中的移动操作添加回调函数。GUI中的移动操作通常包含三个步骤：点击对象、将对象移动到新位置、点击以在新位置放置对象并完成移动。通过指定-edit_type参数，回调函数可以在移动过程的不同阶段（如对象被选中时、移动前或移动后）被触发执行。",
  "usage": "register_gui_edit_callback [-help] -command <string> -edit_type {selection pre-move post-move}",
  "options": [
    {
      "name": "-help",
      "description": "打印此命令的用法信息。如需获取详细描述，请使用man命令。",
      "required": false,
      "type": "flag"
    },
    {
      "name": "-command",
      "description": "指定回调函数的名称。",
      "required": true,
      "type": "string"
    },
    {
      "name": "-edit_type",
      "description": "指定GUI编辑功能（即回调函数触发的时机）：selection（在对象被选中后触发）、pre-move（在对象被放置到新位置前触发）、post-move（在对象移动完成后触发）。",
      "required": true,
      "type": "string"
    }
  ]
}