{
  "command": "connectMacroFeedthrough",
  "is_cmd": true,
  "summary": "连接自定义宏中预定义的穿通引脚到与宏重叠的走线网络",
  "description": "该命令基于布线信息，将自定义宏中预定义的穿通引脚连接到与宏重叠且走线跨越宏的网络。穿通连接的详细信息在一个映射文件中定义，该文件通过 -portmap 参数指定。用户可以包含或排除特定的网络或实例。此命令仅删除已修改网络的布线。该命令可在设计布局和运行早期全局布线后执行。",
  "usage": "connectMacroFeedthrough [-help] [-selectNet <string> | -excludeNet <string> | -selectMarkedNet] [-selectInst <string> | -excludeInst <string>] [-ecoFile <string> | -checkOnly] [-portMap <string>] [-verbose] [-maxSearchDistance <float>] [-searchAllSides] [-abutment <float>] [-abutmentFile <string>] [-floatingPortList <string>]",
  "options": [
    {
      "name": "-help",
      "description": "输出包含每个参数类型和默认信息的简要描述。",
      "required": false,
      "type": "flag"
    },
    {
      "name": "-selectNet",
      "description": "指定仅将穿通缓冲器添加到指定的网络。",
      "required": false,
      "type": "string"
    },
    {
      "name": "-excludeNet",
      "description": "防止将穿通缓冲器添加到指定的网络。",
      "required": false,
      "type": "string"
    },
    {
      "name": "-selectMarkedNet",
      "description": "指定仅将穿通缓冲器添加到当前选中的网络。",
      "required": false,
      "type": "flag"
    },
    {
      "name": "-selectInst",
      "description": "指定仅将穿通缓冲器添加到指定的实例。",
      "required": false,
      "type": "string"
    },
    {
      "name": "-excludeInst",
      "description": "防止为指定的实例添加穿通缓冲器。",
      "required": false,
      "type": "string"
    },
    {
      "name": "-ecoFile",
      "description": "指定将包含变更报告的ECO文件的名称。",
      "required": false,
      "type": "string"
    },
    {
      "name": "-checkOnly",
      "description": "指定仅显示消息报告，而不对网表进行任何更改。",
      "required": false,
      "type": "flag"
    },
    {
      "name": "-portMap",
      "description": "指定包含穿通连接定义的文件名。",
      "required": false,
      "type": "string"
    },
    {
      "name": "-verbose",
      "description": "提供额外的消息，例如网络特定的消息。",
      "required": false,
      "type": "flag"
    },
    {
      "name": "-maxSearchDistance",
      "description": "指定从跨越走线开始，命令应搜索以找到连接的穿通引脚的距离（以微米为单位）。",
      "required": false,
      "type": "float"
    },
    {
      "name": "-searchAllSides",
      "description": "指定如果无法连接同侧最近的可用穿通引脚，命令也应搜索其他侧面的穿通引脚。",
      "required": false,
      "type": "flag"
    },
    {
      "name": "-abutment",
      "description": "指定同一轨道和层上的引脚必须彼此相距的距离，以便被视为邻接。",
      "required": false,
      "type": "float"
    },
    {
      "name": "-abutmentFile",
      "description": "在指定的文件中报告被视为邻接的引脚列表。",
      "required": false,
      "type": "string"
    },
    {
      "name": "-floatingPortList",
      "description": "指定应将未使用端口的列表保存在指定的文件中。",
      "required": false,
      "type": "string"
    }
  ]
}